{"teams":[{"name":"49ERS","keyWords":["49ERS","SAN FRANCISCO","SF"]},{"name":"BEARS","keyWords":["BEARS","CHICAGO","CHI"]},{"name":"BENGALS","keyWords":["BENGALS","CINCINNATI","CIN"]},{"name":"BILLS","keyWords":["BILLS","BUFFALO","BUF"]},{"name":"BRONCOS","keyWords":["BRONCOS","DENVER","DEN"]},{"name":"BROWNS","keyWords":["BROWNS","CLEVELAND",null]},{"name":"BUCCANEERS","keyWords":["BUCCANEERS","TAMPA BAY","TB"]},{"name":"CARDINALS","keyWords":["CARDINALS","ARIZONA","ARI"]},{"name":"CHARGERS","keyWords":["CHARGERS","LOS ANGELES","LAC"]},{"name":"CHIEFS","keyWords":["CHIEFS","KANSAS CITY","KC"]},{"name":"COLTS","keyWords":["COLTS","INDIANAPOLIS","IND"]},{"name":"COWBOYS","keyWords":["COWBOYS","DALLAS","DAL"]},{"name":"DOLPHINS","keyWords":["DOLPHINS","MIAMI","MIA"]},{"name":"EAGLES","keyWords":["EAGLES","PHILADELPHIA","PHI"]},{"name":"FALCONS","keyWords":["FALCONS","ATLANTA","ATL"]},{"name":"GIANTS","keyWords":["GIANTS","NEW YORK","NYG"]},{"name":"JAGUARS","keyWords":["JAGUARS","JACKSONVILLE","JAC"]},{"name":"JETS","keyWords":["JETS","NEW YORK","NYJ"]},{"name":"LIONS","keyWords":["LIONS","DETROIT","DET"]},{"name":"PACKERS","keyWords":["PACKERS","GREEN BAY","GB"]},{"name":"PANTHERS","keyWords":["PANTHERS","CAROLINA","CAR"]},{"name":"PATRIOTS","keyWords":["PATRIOTS","NEW ENGLAND","NE"]},{"name":"RAIDERS","keyWords":["RAIDERS","OAKLAND","OAK"]},{"name":"RAMS","keyWords":["RAMS","LOS ANGELES","LA"]},{"name":"RAVENS","keyWords":["RAVENS","BALTIMORE","BAL"]},{"name":"REDSKINS","keyWords":["REDSKINS","WASHINGTON","WAS"]},{"name":"SAINTS","keyWords":["SAINTS","NEW ORLEANS","NO"]},{"name":"SEAHAWKS","keyWords":["SEAHAWKS","SEATTLE","SEA"]},{"name":"STEELERS","keyWords":["STEELERS","PITTSBURGH","PIT"]},{"name":"TEXANS","keyWords":["TEXANS","HOUSTON","HOU"]},{"name":"TITANS","keyWords":["TITANS","TENNESSEE","TEN"]},{"name":"VIKINGS","keyWords":["VIKINGS","MINNESOTA","MIN"]}]}